gcp_mcp/__init__.py
gcp_mcp/__main__.py
gcp_mcp/server.py
gcp_mcp/gcp_modules/__init__.py
gcp_mcp/gcp_modules/auth/__init__.py
gcp_mcp/gcp_modules/auth/tools.py
gcp_mcp/gcp_modules/billing/__init__.py
gcp_mcp/gcp_modules/billing/tools.py
gcp_mcp/gcp_modules/compute/__init__.py
gcp_mcp/gcp_modules/compute/tools.py
gcp_mcp/gcp_modules/databases/__init__.py
gcp_mcp/gcp_modules/databases/tools.py
gcp_mcp/gcp_modules/deployment/__init__.py
gcp_mcp/gcp_modules/deployment/tools.py
gcp_mcp/gcp_modules/iam/__init__.py
gcp_mcp/gcp_modules/iam/tools.py
gcp_mcp/gcp_modules/kubernetes/__init__.py
gcp_mcp/gcp_modules/kubernetes/tools.py
gcp_mcp/gcp_modules/monitoring/__init__.py
gcp_mcp/gcp_modules/monitoring/tools.py
gcp_mcp/gcp_modules/networking/__init__.py
gcp_mcp/gcp_modules/networking/tools.py
gcp_mcp/gcp_modules/resource_management/__init__.py
gcp_mcp/gcp_modules/resource_management/tools.py
gcp_mcp/gcp_modules/storage/__init__.py
gcp_mcp/gcp_modules/storage/tools.py
gcp_mcp-0.1.0.dist-info/METADATA
gcp_mcp-0.1.0.dist-info/WHEEL
gcp_mcp-0.1.0.dist-info/entry_points.txt
gcp_mcp-0.1.0.dist-info/RECORD
